[
  {
    "type": "mobile",
    "id": "summoned_air_elemental_npc",
    "category": "monster",
    "description": "Converted from ModernUO SummonedAirElemental.",
    "tags": [
      "monster"
    ],
    "body": "0x000D",
    "skinHue": 0,
    "hairHue": 0,
    "strength": 200,
    "dexterity": 200,
    "intelligence": 100,
    "hits": 150,
    "maxHits": 150,
    "stamina": 50,
    "minDamage": 6,
    "maxDamage": 9,
    "armorRating": 40,
    "brain": "mage_combat",
    "skills": {
      "EvalInt": 675,
      "Magery": 675,
      "MagicResist": 675,
      "Tactics": 700,
      "Wrestling": 700
    },
    "sounds": {
      "Idle": 655,
      "StartAttack": 656,
      "Attack": 657,
      "Defend": 658,
      "Die": 659
    },
    "resistances": {
      "physical": 40,
      "fire": 20,
      "cold": 15,
      "poison": 15,
      "energy": 30
    },
    "damageTypes": {
      "physical": 20,
      "energy": 40,
      "cold": 40
    },
    "fixedEquipment": [],
    "randomEquipment": [],
    "title": "an air elemental"
  }
]
